machine_code_analyzer/__init__.py
machine_code_analyzer/llvm_mca_wrapper.py
machine_code_analyzer/uica_wrapper.py
machine_code_analyzer/deps/uiCA/convertXML.py
machine_code_analyzer/deps/uiCA/facile.py
machine_code_analyzer/deps/uiCA/instructions.py
machine_code_analyzer/deps/uiCA/microArchConfigs.py
machine_code_analyzer/deps/uiCA/uiCA.py
machine_code_analyzer/deps/uiCA/utils.py
machine_code_analyzer/deps/uiCA/x64_lib.py
machine_code_analyzer/deps/uiCA/instrData/BDW_data.py
machine_code_analyzer/deps/uiCA/instrData/CFL_data.py
machine_code_analyzer/deps/uiCA/instrData/CLX_data.py
machine_code_analyzer/deps/uiCA/instrData/HSW_data.py
machine_code_analyzer/deps/uiCA/instrData/ICL_data.py
machine_code_analyzer/deps/uiCA/instrData/IVB_data.py
machine_code_analyzer/deps/uiCA/instrData/KBL_data.py
machine_code_analyzer/deps/uiCA/instrData/RKL_data.py
machine_code_analyzer/deps/uiCA/instrData/SKL_data.py
machine_code_analyzer/deps/uiCA/instrData/SKX_data.py
machine_code_analyzer/deps/uiCA/instrData/SNB_data.py
machine_code_analyzer/deps/uiCA/instrData/TGL_data.py
machine_code_analyzer/deps/uiCA/instrData/__init__.py
machine_code_analyzer/deps/uiCA/instrData/uArchInfo.py
machine_code_analyzer/test/__init__.py
machine_code_analyzer/test/test.py
machine_code_analyzer/test/test_llvm_mca.py
machine_code_analyzer-0.1.0.dist-info/licenses/LICENSE
machine_code_analyzer-0.1.0.dist-info/METADATA
machine_code_analyzer-0.1.0.dist-info/WHEEL
machine_code_analyzer-0.1.0.dist-info/entry_points.txt
machine_code_analyzer-0.1.0.dist-info/top_level.txt
machine_code_analyzer-0.1.0.dist-info/RECORD
