Metadata-Version: 2.4
Name: machine_code_analyzer
Version: 0.1.0
Summary: A simple wrapper class around uiCA and llvm-mca, for easier analysing
Author-email: FloydZ <floyd.zweydinger+github@rub.de>
Maintainer-email: FloydZ <floyd.zweydinger+github@rub.de>
Project-URL: Homepage, https://github.com/FloydZ/uICA_wrapper
Project-URL: Repository, https://github.com/FloydZ/uICA_wrapper
Keywords: uica,wrapper
Classifier: Programming Language :: Python :: 3
Classifier: Development Status :: 4 - Beta
Requires-Python: >=3.8
License-File: LICENSE
Requires-Dist: pytest
Requires-Dist: plotly
Requires-Dist: capstone
Dynamic: license-file
